{
    "enabled": true,
    "neededInstalledMods": [],
    "neededUninstalledMods": [],
    "spawns": [
        {
            "id": "psyduck-1",
            "pokemon": "psyduck",
            "type": "pokemon",
            "context": "fishing",
            "bucket": "common",
            "level": "25-35",
            "weight": 1.0,
            "condition": {
                "minX": 4101, "maxX": 4227, "minZ": -198, "maxZ": -99,
                "minLureLevel": 3,
                "maxLureLevel": 3
            }
        },

        {
            "id": "psyduck-2",
            "pokemon": "psyduck",
            "presets": [
                "water"
            ],
            "type": "pokemon",
            "context": "surface",
            "bucket": "common",
            "level": "2-5",
            "weight": 50.0,
            "condition": {
                "minX": 4186, "maxX": 4243, "minZ": 131, "maxZ": 185
            }
        },
        {
            "id": "psyduck-3",
            "pokemon": "psyduck",
            "type": "pokemon",
            "context": "fishing",
            "bucket": "common",
            "level": "15-35",
            "weight": 5.0,
            "condition": {
                "minX": 4186, "maxX": 4243, "minZ": 131, "maxZ": 185,
                "minLureLevel": 3,
                "maxLureLevel": 3
            }
        },

        {
            "id": "psyduck-4",
            "pokemon": "psyduck",
            "presets": [
                "water"
            ],
            "type": "pokemon",
            "context": "surface",
            "bucket": "common",
            "level": "2-5",
            "weight": 50.0,
            "condition": {
                "minX": 4265, "maxX": 4507, "minZ": 139, "maxZ": 250
            }
        },
        {
            "id": "psyduck-5",
            "pokemon": "psyduck",
            "type": "pokemon",
            "context": "fishing",
            "bucket": "common",
            "level": "15-35",
            "weight": 5.0,
            "condition": {
                "minX": 4265, "maxX": 4507, "minZ": 139, "maxZ": 250,
                "minLureLevel": 3,
                "maxLureLevel": 3
            }
        },

        {
            "id": "psyduck-6",
            "pokemon": "psyduck",
            "presets": [
                "water"
            ],
            "type": "pokemon",
            "context": "surface",
            "bucket": "common",
            "level": "20-40",
            "weight": 50.0,
            "condition": {
                "minX": 4379, "maxX": 4529, "minZ": 251, "maxZ": 898
            }
        },
        {
            "id": "psyduck-7",
            "pokemon": "psyduck",
            "type": "pokemon",
            "context": "fishing",
            "bucket": "common",
            "level": "15-35",
            "weight": 5.0,
            "condition": {
                "minX": 4379, "maxX": 4529, "minZ": 251, "maxZ": 898,
                "minLureLevel": 3,
                "maxLureLevel": 3
            }
        },

        {
            "id": "psyduck-8",
            "pokemon": "psyduck",
            "type": "pokemon",
            "context": "fishing",
            "bucket": "common",
            "level": "25-35",
            "weight": 1.0,
            "condition": {
                "minX": 3236, "maxX": 3619, "minZ": 804, "maxZ": 947,
                "minLureLevel": 3,
                "maxLureLevel": 3
            }
        },

        {
            "id": "psyduck-9",
            "pokemon": "psyduck",
            "type": "pokemon",
            "context": "fishing",
            "bucket": "common",
            "level": "25-35",
            "weight": 1.0,
            "condition": {
                "minX": 3006, "maxX": 3235, "minZ": 804, "maxZ": 973,
                "minLureLevel": 3,
                "maxLureLevel": 3
            }
        },

        {
            "id": "psyduck-10",
            "pokemon": "psyduck",
            "presets": [
                "water"
            ],
            "type": "pokemon",
            "context": "surface",
            "bucket": "common",
            "level": "30-55",
            "weight": 50.0,
            "condition": {
                "minX": 2779, "maxX": 3015, "minY": 60, "maxY": 89, "minZ": 1845, "maxZ": 1994
            }
        },
        {
            "id": "psyduck-11",
            "pokemon": "psyduck",
            "type": "pokemon",
            "context": "fishing",
            "bucket": "common",
            "level": "15-35",
            "weight": 5.0,
            "condition": {
                "minX": 2779, "maxX": 3015, "minY": 60, "maxY": 89, "minZ": 1845, "maxZ": 1994,
                "minLureLevel": 3,
                "maxLureLevel": 3
            }
        },
        {
            "id": "psyduck-12",
            "pokemon": "psyduck",
            "presets": [
                "water"
            ],
            "type": "pokemon",
            "context": "surface",
            "bucket": "common",
            "level": "40-65",
            "weight": 50.0,
            "condition": {
                "minX": 2779, "maxX": 3015, "minY": 60, "maxY": 89, "minZ": 1845, "maxZ": 1994
            }
        },
        {
            "id": "psyduck-13",
            "pokemon": "psyduck",
            "type": "pokemon",
            "context": "fishing",
            "bucket": "common",
            "level": "15-35",
            "weight": 4.0,
            "condition": {
                "minX": 2779, "maxX": 3015, "minY": 60, "maxY": 89, "minZ": 1845, "maxZ": 1994,
                "minLureLevel": 3,
                "maxLureLevel": 3
            }
        },

        {
            "id": "psyduck-14",
            "pokemon": "psyduck",
            "type": "pokemon",
            "context": "fishing",
            "bucket": "common",
            "level": "25-35",
            "weight": 1.0,
            "condition": {
                "minX": 3053, "maxX": 3170, "minZ": 974, "maxZ": 1098,
                "minLureLevel": 3,
                "maxLureLevel": 3
            }
        },

        {
            "id": "psyduck-15",
            "pokemon": "psyduck",
            "presets": [
                "water"
            ],
            "type": "pokemon",
            "context": "surface",
            "bucket": "common",
            "level": "8-14",
            "weight": 50.0,
            "condition": {
                "minX": 2725, "maxX": 3170, "minZ": 1099, "maxZ": 1190
            }
        },
        {
            "id": "psyduck-16",
            "pokemon": "psyduck",
            "type": "pokemon",
            "context": "fishing",
            "bucket": "common",
            "level": "15-35",
            "weight": 5.0,
            "condition": {
                "minX": 2725, "maxX": 3170, "minZ": 1099, "maxZ": 1190,
                "minLureLevel": 3,
                "maxLureLevel": 3
            }
        },

        {
            "id": "psyduck-17",
            "pokemon": "psyduck",
            "type": "pokemon",
            "context": "fishing",
            "bucket": "common",
            "level": "15-35",
            "weight": 1.0,
            "condition": {
                "minX": 2483, "maxX": 2637, "minZ": 556, "maxZ": 938,
                "minLureLevel": 3,
                "maxLureLevel": 3
            }
        },

        {
            "id": "psyduck-18",
            "pokemon": "psyduck",
            "type": "pokemon",
            "context": "fishing",
            "bucket": "common",
            "level": "15-35",
            "weight": 1.0,
            "condition": {
                "minX": 2483, "maxX": 2679, "minZ": -154, "maxZ": 425,
                "minLureLevel": 3,
                "maxLureLevel": 3
            }
        },

        {
            "id": "psyduck-19",
            "pokemon": "psyduck",
            "presets": [
                "water"
            ],
            "type": "pokemon",
            "context": "surface",
            "bucket": "common",
            "level": "13-16",
            "weight": 50.0,
            "condition": {
                "minX": 3042, "maxX": 3174, "minZ": 215, "maxZ": 386
            }
        },

        {
            "id": "psyduck-20",
            "pokemon": "psyduck",
            "type": "pokemon",
            "context": "fishing",
            "bucket": "common",
            "level": "15-35",
            "weight": 5.0,
            "condition": {
                "minX": 3042, "maxX": 3174, "minZ": 215, "maxZ": 386,
                "minLureLevel": 3,
                "maxLureLevel": 3
            }
        },

        {
            "id": "psyduck-21",
            "pokemon": "psyduck",
            "type": "pokemon",
            "context": "fishing",
            "bucket": "common",
            "level": "15-35",
            "weight": 1.0,
            "condition": {
                "minX": 2680, "maxX": 2975, "minZ": 30, "maxZ": 159,
                "minLureLevel": 3,
                "maxLureLevel": 3
            }
        },

        {
            "id": "psyduck-22",
            "pokemon": "psyduck",
            "presets": [
                "water"
            ],
            "type": "pokemon",
            "context": "surface",
            "bucket": "common",
            "level": "11-17",
            "weight": 49.0,
            "condition": {
                "minX": 3335, "maxX": 3637, "minZ": 396, "maxZ": 599
            }
        },

        {
            "id": "psyduck-23",
            "pokemon": "psyduck",
            "type": "pokemon",
            "context": "fishing",
            "bucket": "common",
            "level": "15-35",
            "weight": 1.0,
            "condition": {
                "minX": 2976, "maxX": 3235, "minZ": 3, "maxZ": 214,
                "minLureLevel": 3,
                "maxLureLevel": 3
            }
        },

        {
            "id": "psyduck-24",
            "pokemon": "psyduck",
            "type": "pokemon",
            "context": "fishing",
            "bucket": "common",
            "level": "15-35",
            "weight": 1.0,
            "condition": {
                "minX": 2680, "maxX": 2975, "minZ": 30, "maxZ": 159,
                "minLureLevel": 3,
                "maxLureLevel": 3
            }
        },

        {
            "id": "psyduck-25",
            "pokemon": "psyduck",
            "presets": [
                "water"
            ],
            "type": "pokemon",
            "context": "surface",
            "bucket": "common",
            "level": "20-29",
            "weight": 50.0,
            "condition": {
                "minX": 3333, "maxX": 3607, "minZ": -489, "maxZ": -295
            }
        },

        {
            "id": "psyduck-26",
            "pokemon": "psyduck",
            "type": "pokemon",
            "context": "fishing",
            "bucket": "common",
            "level": "15-35",
            "weight": 5.0,
            "condition": {
                "minX": 3333, "maxX": 3607, "minZ": -489, "maxZ": -295,
                "minLureLevel": 3,
                "maxLureLevel": 3
            }
        },

        {
            "id": "psyduck-27",
            "pokemon": "psyduck",
            "presets": [
                "water"
            ],
            "type": "pokemon",
            "context": "surface",
            "bucket": "common",
            "level": "22-31",
            "weight": 50.0,
            "condition": {
                "minX": 3194, "maxX": 3711, "minZ": -294, "maxZ": -45
            }
        },
        {
            "id": "psyduck-28",
            "pokemon": "psyduck",
            "type": "pokemon",
            "context": "fishing",
            "bucket": "common",
            "level": "15-35",
            "weight": 5.0,
            "condition": {
                "minX": 3194, "maxX": 3711, "minZ": -294, "maxZ": -45,
                "minLureLevel": 3,
                "maxLureLevel": 3
            }
        },

        {
            "id": "psyduck-29",
            "pokemon": "psyduck",
            "type": "pokemon",
            "context": "fishing",
            "bucket": "common",
            "level": "15-35",
            "weight": 1.0,
            "condition": {
                "minX": 2483, "maxX": 2977, "minZ": -233, "maxZ": -155,
                "minLureLevel": 3,
                "maxLureLevel": 3
            }
        },

        {
            "id": "psyduck-30",
            "pokemon": "psyduck",
            "type": "pokemon",
            "context": "fishing",
            "bucket": "common",
            "level": "15-35",
            "weight": 1.0,
            "condition": {
                "minX": 3373, "maxX": 3537, "minZ": -839, "maxZ": -490,
                "minLureLevel": 3,
                "maxLureLevel": 3
            }
        },

        {
            "id": "psyduck-31",
            "pokemon": "psyduck",
            "type": "pokemon",
            "context": "fishing",
            "bucket": "common",
            "level": "15-35",
            "weight": 1.0,
            "condition": {
                "minX": 3538, "maxX": 4097, "minZ": -839, "maxZ": -490,
                "minLureLevel": 3,
                "maxLureLevel": 3
            }
        },


        {
            "id": "psyduck-32",
            "pokemon": "psyduck",
            "type": "pokemon",
            "context": "grounded",
            "bucket": "common",
            "level": "26-33",
            "weight": 28,
            "condition": {
                "canSeeSky": false,
                "minX": 3506, "maxX": 3712, "minY": 120, "maxY": 138, "minZ": 1641, "maxZ": 1774
            }
        },
        {
            "id": "psyduck-33",
            "pokemon": "psyduck",
            "type": "pokemon",
            "context": "grounded",
            "bucket": "common",
            "level": "29-31",
            "weight": 20,
            "condition": {
                "canSeeSky": false,
                "minX": 3506, "maxX": 3712, "minY": 102, "maxY": 119, "minZ": 1641, "maxZ": 1774
            }
        },
        {
            "id": "psyduck-34",
            "pokemon": "psyduck",
            "type": "pokemon",
            "context": "grounded",
            "bucket": "common",
            "level": "30-32",
            "weight": 20,
            "condition": {
                "canSeeSky": false,
                "minX": 3506, "maxX": 3712, "minY": 87, "maxY": 101, "minZ": 1641, "maxZ": 1774
            }
        },
        {
            "id": "psyduck-35",
            "pokemon": "psyduck",
            "type": "pokemon",
            "context": "grounded",
            "bucket": "common",
            "level": "30-32",
            "weight": 10,
            "condition": {
                "canSeeSky": false,
                "minX": 3506, "maxX": 3712, "minY": 65, "maxY": 86, "minZ": 1641, "maxZ": 1774
            }
        },
        {
            "id": "psyduck-36",
            "pokemon": "psyduck",
            "type": "pokemon",
            "context": "grounded",
            "bucket": "common",
            "level": "32",
            "weight": 10,
            "condition": {
                "canSeeSky": false,
                "minX": 3506, "maxX": 3712, "minY": 33, "maxY": 64, "minZ": 1641, "maxZ": 1774
            }
        },

        {
            "id": "psyduck-37",
            "pokemon": "psyduck",
            "presets": [
                "water"
            ],
            "type": "pokemon",
            "context": "surface",
            "bucket": "common",
            "level": "30-40",
            "weight": 4.0,
            "condition": {
                "canSeeSky": false,
                "minX": 3506, "maxX": 3712, "minY": 33, "maxY": 86, "minZ": 1641, "maxZ": 1774
            }
        },

        {
            "id": "psyduck-38",
            "pokemon": "psyduck",
            "type": "pokemon",
            "context": "fishing",
            "bucket": "common",
            "level": "15-35",
            "weight": 4.0,
            "condition": {
                "minX": 3506, "maxX": 3712, "minY": 33, "maxY": 86, "minZ": 1641, "maxZ": 1774,
                "minLureLevel": 3,
                "maxLureLevel": 3
            }
        },

        {
            "id": "psyduck-39",
            "pokemon": "psyduck",
            "type": "pokemon",
            "context": "fishing",
            "bucket": "common",
            "level": "15-35",
            "weight": 1.0,
            "condition": {
                "minX": 4098, "maxX": 4244, "minZ": -793, "maxZ": -654,
                "minLureLevel": 3,
                "maxLureLevel": 3
            }
        },

        {
            "id": "psyduck-40",
            "pokemon": "psyduck",
            "type": "pokemon",
            "context": "fishing",
            "bucket": "common",
            "level": "15-35",
            "weight": 1.0,
            "condition": {
                "minX": 4098, "maxX": 4227, "minZ": -653, "maxZ": -199,
                "minLureLevel": 3,
                "maxLureLevel": 3
            }
        }

    ]
}
