{
    "enabled": true,
    "neededInstalledMods": [],
    "neededUninstalledMods": [],
    "spawns": [
        {
            "id": "seaking-1",
            "pokemon": "seaking",
            "type": "pokemon",
            "context": "fishing",
            "bucket": "common",
            "level": "20-30",
            "weight": 40.0,
            "condition": {
                "minX": 3333, "maxX": 3607, "minZ": -489, "maxZ": -295,
                "minLureLevel": 3,
                "maxLureLevel": 3
            }
        },

        {
            "id": "seaking-2",
            "pokemon": "seaking",
            "type": "pokemon",
            "context": "fishing",
            "bucket": "common",
            "level": "20-30",
            "weight": 40.0,
            "condition": {
                "minX": 3194, "maxX": 3711, "minZ": -294, "maxZ": -45,
                "minLureLevel": 3,
                "maxLureLevel": 3
            }
        },

        {
            "id": "seaking-3",
            "pokemon": "seaking",
            "type": "pokemon",
            "context": "fishing",
            "bucket": "common",
            "level": "20-30",
            "weight": 40.0,
            "condition": {
                "minX": 3244, "maxX": 3440, "minZ": -1551, "maxZ": -1287,
                "minLureLevel": 3,
                "maxLureLevel": 3
            }
        }
    ]
}
